amipy/__init__.py
amipy/cmd.py
amipy/exceptions.py
amipy/request.py
amipy/response.py
amipy/spider.py
amipy/BaseClass/__init__.py
amipy/BaseClass/orm.py
amipy/commands/__init__.py
amipy/commands/cproject.py
amipy/commands/cspider.py
amipy/commands/list.py
amipy/commands/runproject.py
amipy/commands/runspider.py
amipy/config/__init__.py
amipy/config/project_settings.py
amipy/config/spider_settings.py
amipy/core/__init__.py
amipy/core/crawler.py
amipy/core/loader.py
amipy/core/looper.py
amipy/core/scheduler.py
amipy/core/serverthread.py
amipy/core/spiderhub.py
amipy/core/workstation.py
amipy/crawl/__init__.py
amipy/crawl/requester/__init__.py
amipy/crawl/requester/common.py
amipy/crawl/requester/media.py
amipy/datatype/__init__.py
amipy/datatype/queue.py
amipy/log/__init__.py
amipy/middlewares/CrawlFilter.py
amipy/middlewares/HttpProxy.py
amipy/middlewares/ServerCtrl.py
amipy/middlewares/__init__.py
amipy/middlewares/requestwares/HeadersHandle.py
amipy/middlewares/requestwares/ListHandle.py
amipy/middlewares/requestwares/Robotstxt.py
amipy/middlewares/requestwares/Rules.py
amipy/middlewares/requestwares/__init__.py
amipy/middlewares/responsewares/RetryPages.py
amipy/middlewares/responsewares/__init__.py
amipy/subcmd/__init__.py
amipy/subcmd/close.py
amipy/subcmd/echo.py
amipy/subcmd/help.py
amipy/subcmd/list.py
amipy/subcmd/pause.py
amipy/subcmd/restart.py
amipy/subcmd/resume.py
amipy/subcmd/show.py
amipy/subcmd/stop.py
amipy/templates/project/__init__.py
amipy/templates/project/settings.py.tpl
amipy/templates/project/spiders/__init__.py
amipy/templates/spider/__init__.py
amipy/templates/spider/cookies.info
amipy/templates/spider/item.py.tpl
amipy/templates/spider/settings.py.tpl
amipy/templates/spider/site_record.info
amipy/templates/spider/spider.py.tpl
amipy/templates/spider/url_record.info
amipy/util/__init__.py
amipy/util/dbhelper.py
amipy/util/file.py
amipy/util/filter.py
amipy/util/http.py
amipy/util/load.py
amipy/util/proxy.py
amipy/util/string.py
Amipy-1.0.2.dist-info/LICENSE
Amipy-1.0.2.dist-info/METADATA
Amipy-1.0.2.dist-info/WHEEL
Amipy-1.0.2.dist-info/entry_points.txt
Amipy-1.0.2.dist-info/top_level.txt
Amipy-1.0.2.dist-info/RECORD
