Metadata-Version: 2.1
Name: Amipy
Version: 1.0.2
Summary: A micro asynchronous Python website crawler framework
Home-page: https://github.com/01ly/Amipy
Author: linkin
Maintainer: linkin
Maintainer-email: yooleak@outlook.com 
License: MIT
Platform: UNKNOWN
Classifier: Environment :: Console
Classifier: License :: OSI Approved :: MIT License
Classifier: Operating System :: OS Independent
Classifier: Programming Language :: Python
Classifier: Programming Language :: Python :: 3.5
Classifier: Programming Language :: Python :: 3.6
Classifier: Programming Language :: Python :: 3.7
Classifier: Topic :: Internet :: WWW/HTTP
Classifier: Topic :: Software Development :: Libraries :: Application Frameworks
Classifier: Topic :: Software Development :: Libraries :: Python Modules
Requires-Python: >=3.5
Requires-Dist: lxml
Requires-Dist: bs4
Requires-Dist: six (>=1.5.2)
Requires-Dist: bloompy (>=0.1.1)
